{
	"class" : {
		 },
	"instance" : {
		"accept" : "dkh 3/26/2014 14:22",
		"acceptContents:notifying:" : "dkh 3/29/2013 13:23",
		"activateModel:" : "dkh 3/26/2014 10:03",
		"bindingOf:" : "dkh 12/27/2012 09:50",
		"buildCmdActionMapFor:" : "dkh 3/25/2014 21:53",
		"buildTextMorph" : "dkh 2/21/2014 17:57",
		"cancel" : "dkh 3/26/2014 14:23",
		"clientElement:" : "dkh 1/26/2013 09:32",
		"cmdBPressed:" : "dkh 2/7/2013 15:47",
		"cmdKPressed:" : "dkh 2/7/2013 15:47",
		"cmdMPressed:" : "dkh 2/7/2013 15:45",
		"cmdNPressed:" : "dkh 2/7/2013 15:47",
		"cmdShiftBPressed:" : "dkh 2/7/2013 15:47",
		"cmdShiftNPressed:" : "dkh 2/7/2013 15:47",
		"codeMenu:" : "dkh 2/21/2014 17:57",
		"contents" : "dkh 1/26/2013 09:32",
		"copySelection" : "dkh 3/26/2014 14:23",
		"cutSelection" : "dkh 3/26/2014 14:23",
		"doItContext" : "dkh 12/27/2012 08:10",
		"doItReceiver" : "dkh 2/7/2013 10:22",
		"editorSource" : "dkh 2/7/2013 15:39",
		"edittingCode" : "dkh 12/27/2012 08:10",
		"edittingCode:" : "dkh 12/27/2012 08:10",
		"executeKeybinding:actionSymbol:" : "dkh 3/26/2014 09:43",
		"executeMenuAction:" : "dkh 3/25/2014 12:01",
		"flash" : "dkh 2/23/2014 17:34",
		"getSelection" : "dkh 2/7/2013 15:42",
		"hasBindingThatBeginsWith:" : "dkh 12/27/2012 08:10",
		"insertAfterSelection:" : "dkh 3/26/2014 14:25",
		"morph" : "dkh 12/27/2012 08:10",
		"pasteRecent" : "dkh 3/26/2014 14:23",
		"pasteSelection" : "dkh 3/26/2014 14:23",
		"refreshView" : "dkh 3/26/2014 10:12",
		"replaceSelectionWith:" : "dkh 3/24/2014 20:59",
		"shoutAboutToStyle:" : "dkh 1/26/2013 09:32",
		"spawnWindow" : "dkh 3/26/2014 10:05",
		"stylerClass" : "dkh 12/27/2012 08:10",
		"textMorph" : "dkh 12/27/2012 08:10",
		"theEditor" : "dkh 2/23/2014 17:27" } }
