{
	"class" : {
		"haloRunBlock:" : "DataCurator 01/01/2013 14:39",
		"haloWindowBlock:" : "DataCurator 01/01/2013 14:31",
		"halos" : "DataCurator 12/11/2012 20:54",
		"halosManPage" : "dkh 12/01/2012 16:44",
		"installHalosOn:" : "DataCurator 01/01/2013 21:27",
		"installOn:" : "dkh 12/01/2012 16:44",
		"priority" : "DataCurator 12/19/2012 11:44",
		"readMeNode" : "DataCurator 12/20/2012 07:39",
		"readMeRun" : "DataCurator 12/20/2012 07:39",
		"readMeSelf" : "DataCurator 12/20/2012 07:40",
		"readMeWindow" : "DataCurator 12/20/2012 07:40",
		"toolName" : "dkh 12/01/2012 16:44",
		"toolReadMe" : "dkh 12/01/2012 16:44" },
	"instance" : {
		"halos" : "dkh 12/01/2012 16:44" } }
