{
	"class" : {
		 },
	"instance" : {
		"baseClassDefinitionList" : "dkh 10/05/2013 11:34",
		"browseClassDefinitionMenuAction:selectionIndex:" : "dkh 10/05/2013 11:34",
		"classDefinitionList" : "dkh 05/10/2014 08:01",
		"classHierarchy:" : "dkh 10/05/2013 11:34",
		"clientList:" : "dkh 04/20/2014 12:37",
		"copyObjectMenuAction:selectionIndex:" : "dkh 06/25/2015 16:16",
		"createAccessorsMenuAction:selectionIndex:" : "dkh 04/27/2014 07:11",
		"cutObjectMenuAction:selectionIndex:" : "dkh 06/25/2015 16:16",
		"defaultEditorWindowLocation" : "DataCurator 01/27/2013 21:13",
		"editorWindowLabel" : "dkh 06/03/2014 13:52",
		"itemSelected:at:shiftPressed:" : "dkh 08/11/2015 12:11",
		"menuActionSpec" : "dkh 06/23/2014 19:58",
		"pasteObjectMenuAction:selectionIndex:" : "dkh 06/20/2014 12:10",
		"selectedClass:selectionIndex:" : "DataCurator 02/07/2013 14:30",
		"selectedDefinition:selectionIndex:" : "dkh 10/05/2013 11:34" } }
