{
	"class" : {
		 },
	"instance" : {
		"add:" : "AlexandreBergel 4/8/2015 11:58",
		"addAll:" : "AlexandreBergel 1/22/2015 18:05",
		"clean" : "AlexandreBergel 4/8/2015 12:00",
		"createView" : "AlexandreBergel 1/22/2015 09:40",
		"example01" : "AlexandreBergel 5/5/2015 20:02",
		"example02" : "AlexandreBergel 4/8/2015 11:58",
		"initialize" : "AlexandreBergel 4/8/2015 11:59",
		"renderIn:" : "AlexandreBergel 1/22/2015 10:02",
		"resetAddedElements" : "AlexandreBergel 4/8/2015 11:59",
		"updateView" : "AlexandreBergel 4/8/2015 12:00",
		"x" : "AlexandreBergel 1/22/2015 18:04",
		"x:" : "AlexandreBergel 1/22/2015 18:04",
		"y" : "AlexandreBergel 1/22/2015 18:04",
		"y:" : "AlexandreBergel 1/22/2015 18:04" } }
