{
	"class" : {
		 },
	"instance" : {
		"browseProjectCategoriesMenuAction:selectionIndex:" : "dkh 05/20/2014 07:47",
		"browseProjectClassesMenuAction:selectionIndex:" : "dkh 05/16/2014 14:51",
		"browseProjectDirtyPackagesMenuAction:selectionIndex:" : "dkh 05/29/2014 15:20",
		"browseProjectPackagesMenuAction:selectionIndex:" : "dkh 05/23/2014 10:21",
		"browseProjectRepositoriesMenuAction:selectionIndex:" : "dkh 05/29/2014 15:50",
		"clientList:listElement:" : "dkh 05/23/2014 12:00",
		"cloneProjectMenuAction:selectionIndex:" : "dkh 05/23/2014 12:17",
		"commitLogMenuAction:selectionIndex:" : "dkh 05/20/2014 10:21",
		"commitProjectMenuAction:selectionIndex:" : "dkh 05/28/2014 19:04",
		"configuration:newVersion:" : "dkh 05/23/2014 12:17",
		"configurationCommitLogMenuAction:selectionIndex:" : "dkh 05/20/2014 10:58",
		"configurationMenuActionSpec" : "dkh 05/17/2014 08:08",
		"createConfigurationNewMajorVersionMenuAction:selectionIndex:" : "dkh 05/20/2014 10:08",
		"createConfigurationNewMinorVersionMenuAction:selectionIndex:" : "dkh 05/20/2014 10:08",
		"createConfigurationNewPatchVersionMenuAction:selectionIndex:" : "dkh 05/20/2014 10:08",
		"createReleaseConfigurationVersionMenuAction:selectionIndex:" : "dkh 05/23/2014 12:17",
		"diffMenuAction:selectionIndex:" : "dkh 05/23/2014 12:17",
		"editProjectFileMenuAction:selectionIndex:" : "dkh 05/20/2014 11:56",
		"getProjectMenuAction:selectionIndex:" : "dkh 05/23/2014 12:17",
		"gitBranchesMenuAction:selectionIndex:" : "dkh 05/28/2014 16:32",
		"gitCheckoutMenuAction:selectionIndex:" : "dkh 05/29/2014 16:58",
		"gitCommitLogMenuAction:selectionIndex:" : "dkh 05/16/2014 16:10",
		"gitDiffCachedMenuAction:selectionIndex:" : "dkh 05/29/2014 11:16",
		"gitDiffMenuAction:selectionIndex:" : "dkh 05/28/2014 18:27",
		"gitFetchMenuAction:selectionIndex:" : "dkh 05/28/2014 16:24",
		"gitMergeProjectMenuAction:selectionIndex:" : "dkh 05/29/2014 17:15",
		"gitPullProjectMenuAction:selectionIndex:" : "dkh 05/28/2014 15:54",
		"gitPushProjectMenuAction:selectionIndex:" : "dkh 05/28/2014 15:53",
		"gitStatusMenuAction:selectionIndex:" : "dkh 05/16/2014 08:17",
		"gitVersionSkewDiffMenuAction:selectionIndex:" : "dkh 05/20/2014 06:31",
		"gitVersionSkewSaveProjectMenuAction:selectionIndex:" : "dkh 05/29/2014 17:16",
		"hasGitRepository:" : "dkh 05/12/2014 17:05",
		"itemSelected:listElement:selectedIndex:shiftPressed:" : "dkh 05/28/2014 18:59",
		"loadConfigurationVersionMenuAction:selectionIndex:" : "dkh 05/16/2014 16:50",
		"loadProjectMenuAction:selectionIndex:" : "dkh 05/23/2014 12:17",
		"lockProjectMenuAction:selectionIndex:" : "dkh 05/23/2014 12:17",
		"menuActionSpec:" : "dkh 05/29/2014 16:54",
		"projectBlock" : "dkh 05/07/2014 11:19",
		"projectBlock:" : "dkh 05/07/2014 11:19",
		"projectTool" : "dkh 05/12/2014 17:02",
		"projectTool:" : "dkh 05/12/2014 17:02",
		"projects" : "dkh 05/07/2014 11:20",
		"projects:" : "dkh 05/07/2014 11:19",
		"refreshListMenuAction:selectionIndex:" : "dkh 05/23/2014 12:23",
		"revertProjectMenuAction:selectionIndex:" : "dkh 05/23/2014 12:17",
		"switchConfigurationVersionMenuAction:selectionIndex:" : "dkh 05/23/2014 12:17",
		"unlockProjectMenuAction:selectionIndex:" : "dkh 05/23/2014 12:17",
		"unregisterProjectMenuAction:selectionIndex:" : "dkh 05/23/2014 12:17",
		"windowLocation" : "dkh 05/23/2014 10:16",
		"windowName" : "dkh 05/07/2014 11:37" } }
