{
	"class" : {
		"classesReadMe" : "DataCurator 11/30/2012 11:49",
		"globalsReadMe" : "DataCurator 11/30/2012 11:50",
		"installOn:" : "DataCurator 11/30/2012 10:40",
		"stClassesNode:" : "DataCurator 11/30/2012 11:50",
		"stGlobalsNode:" : "DataCurator 11/30/2012 12:19",
		"stSymbolListNode:" : "DataCurator 11/30/2012 12:14",
		"symbolDictionaryNodeFor:parentNode:topez:" : "DataCurator 11/30/2012 12:09",
		"symbolDictionaryReadMe:" : "DataCurator 11/30/2012 12:02",
		"symbolListReadMe" : "DataCurator 11/30/2012 12:15",
		"toolName" : "DataCurator 11/30/2012 10:40",
		"toolReadMe" : "DataCurator 11/30/2012 10:40" },
	"instance" : {
		 } }
