{
	"class" : {
		"disableFullCompression" : "dkh 2/27/2008 12:04",
		"enableFullCompression" : "dkh 2/27/2008 12:04",
		"fullCompressionEnabled" : "dkh 2/27/2008 12:02",
		"gsCursor" : "dkh 1/10/2013 08:10",
		"initGsCursor" : "dkh 1/10/2013 08:10",
		"new" : "JGF 4/2/2007 12:59" },
	"instance" : {
		"actAsExecutor" : "dkh 2/17/2009 15:41",
		"asOopType:" : "dkh 9/29/2012 17:48",
		"clearStack:" : "dkh 1/5/2013 12:08",
		"clientForwarderCache" : "dkh 11/18/2012 08:22",
		"clientObjectForwardedFrom:" : "dkh 11/18/2012 08:22",
		"continue:" : "dkh 1/10/2013 08:14",
		"continueWith:replaceTopOfStackWith:" : "dkh 1/10/2013 08:14",
		"executeStringExpectingStringNB:" : "dkh 1/10/2013 08:15",
		"executeStringNB:" : "dkh 11/13/2012 12:25",
		"finalize" : "dkh 2/17/2009 15:41",
		"gemHost" : "JGF 4/2/2007 15:39",
		"gemNRS:" : "JGF 1/31/2007 14:57",
		"gemType" : "JGF 4/2/2007 15:38",
		"getAndClearLastError" : "dkh 10/1/2007 13:47",
		"getNbResult" : "dkh 1/5/2013 14:13",
		"getNbResultAsBoolean" : "JGF 4/6/2007 15:00",
		"getNbResultAsOop" : "dkh 12/28/2012 20:44",
		"getNbResultAsString" : "dkh 1/5/2013 11:37",
		"getNbResultAsVoid" : "JGF 4/6/2007 15:00",
		"getSessionNumber" : "dkh 1/5/2013 12:06",
		"hardBreak" : "dkh 1/5/2013 11:38",
		"initialize" : "dkh 11/18/2012 08:49",
		"integerToOop:" : "dkh 1/5/2013 12:09",
		"isCallInProgress" : "dkh 1/5/2013 11:39",
		"isValid" : "dkh 8/16/2007 13:39",
		"library" : "JGF 4/2/2007 11:37",
		"login:" : "jgf 4/2/2008 13:39",
		"login:osUser:osPassword:" : "dkh 1/10/2013 08:12",
		"logout" : "dkh 1/5/2013 11:40",
		"nbPollForResult" : "dkh 1/5/2013 13:19",
		"newString:" : "dkh 9/29/2012 14:13",
		"newStringOopType:" : "dkh 1/5/2013 12:09",
		"number" : "JGF 1/31/2007 15:09",
		"printOn:" : "dkh 2/13/2009 13:20",
		"rawExecuteStringNB:" : "dkh 1/10/2013 08:13",
		"rawReceiverNB:perform:withArgs:" : "dkh 1/10/2013 08:13",
		"receiverNB:perform:withArgs:" : "dkh 11/13/2012 12:20",
		"receiverNB:performNoDebug:withArgs:" : "dkh 1/5/2013 12:10",
		"registerClientObjectForwarder:" : "dkh 11/18/2012 08:44",
		"release" : "dkh 9/26/2012 13:51",
		"setSession" : "dkh 1/5/2013 11:45",
		"signalServerError:" : "dkh 12/28/2012 19:06",
		"softBreak" : "dkh 1/5/2013 11:46",
		"stepIntoWith:" : "dkh 9/29/2012 09:57",
		"stepOverWith:" : "dkh 9/29/2012 09:57",
		"stepWith:level:" : "dkh 1/10/2013 08:13",
		"stoneHost" : "JGF 4/2/2007 15:35",
		"stoneNRS:" : "JGF 1/31/2007 14:58",
		"stoneName" : "JGF 4/2/2007 15:37",
		"terminateCurrentNbCall" : "dkh 1/5/2013 14:15",
		"unregisterClientObjectForwarder:" : "dkh 11/18/2012 09:08",
		"userID" : "JGF 4/2/2007 15:40",
		"userID:" : "JGF 1/31/2007 15:01" } }
